pactus/__init__.py
pactus/config.py
pactus/dataset/__init__.py
pactus/dataset/_utils.py
pactus/dataset/dataset.py
pactus/models/__init__.py
pactus/models/decision_tree_model.py
pactus/models/evaluation.py
pactus/models/evaluation_comparison.py
pactus/models/kneighbors_model.py
pactus/models/lstm_model.py
pactus/models/model.py
pactus/models/random_forest_model.py
pactus/models/svm_model.py
pactus/models/transformer.py
pactus/models/transformer_model.py
pactus/models/xgboost_model.py
pactus-0.4.3.dist-info/LICENSE
pactus-0.4.3.dist-info/METADATA
pactus-0.4.3.dist-info/WHEEL
pactus-0.4.3.dist-info/top_level.txt
pactus-0.4.3.dist-info/RECORD
