Metadata-Version: 2.1
Name: pactus
Version: 0.4.3
Summary: Framework to evaluate Trajectory Classification Algorithms
Author-email: Jorge Morgado Vega <jorge.morgadov@gmail.com>, Gustavo Viera-López <gvieralopez@gmail.com>, Alfredo Reyes <areyes@fisica.uh.cu>
License: MIT License
Project-URL: Homepage, https://github.com/yupidevs/pactus
Keywords: trajectory,classification
Classifier: License :: OSI Approved :: MIT License
Classifier: Programming Language :: Python
Classifier: Programming Language :: Python :: 3
Requires-Python: >=3.8
License-File: LICENSE
Requires-Dist: numpy >=1.23.5
Requires-Dist: yupi >=0.11.2
Requires-Dist: tensorflow >=2.12.0
Requires-Dist: scikit-learn >=1.1.1
Requires-Dist: xgboost >=1.7.4
Requires-Dist: GitPython >=3.1.29
Requires-Dist: requests >=2.32.3
Provides-Extra: dev
Requires-Dist: mypy ; extra == 'dev'
Requires-Dist: black ; extra == 'dev'
Requires-Dist: pylint ; extra == 'dev'
Requires-Dist: bumpver ; extra == 'dev'
Requires-Dist: isort ; extra == 'dev'
Requires-Dist: pytest ; extra == 'dev'
Requires-Dist: tensor-annotations-tensorflow-stubs ; extra == 'dev'
